SendDeploy/__init__.py
SendDeploy/cli.py
senddeploy-0.0.9.dist-info/METADATA
senddeploy-0.0.9.dist-info/WHEEL
senddeploy-0.0.9.dist-info/entry_points.txt
senddeploy-0.0.9.dist-info/licenses/LICENSE
senddeploy-0.0.9.dist-info/RECORD
