Metadata-Version: 2.3
Name: SendDeploy
Version: 0.0.9
Summary: A CLI tool to upload files via SCP from Windows
Project-URL: Homepage, https://github.com/Juliyo/SendDeploy
Project-URL: Issues, https://github.com/Juliyo/SendDeploy/issues
Author-email: Julio Zamora <julio17795@gmail.com>
Requires-Dist: paramiko
Requires-Dist: scp
Requires-Dist: tqdm
Requires-Dist: windows-curses
